PyXTaf-0.5.1.64.dist-info/METADATA
PyXTaf-0.5.1.64.dist-info/RECORD
PyXTaf-0.5.1.64.dist-info/WHEEL
PyXTaf-0.5.1.64.dist-info/namespace_packages.txt
PyXTaf-0.5.1.64.dist-info/top_level.txt
PyXTaf-0.5.1.64.dist-info/zip-safe
taf/__init__.py
taf/taf.py
taf/foundation/__init__.py
taf/foundation/servicelocator.py
taf/foundation/api/__init__.py
taf/foundation/api/cli/__init__.py
taf/foundation/api/cli/client.py
taf/foundation/api/plugins/__init__.py
taf/foundation/api/plugins/baseplugin.py
taf/foundation/api/plugins/cliplugin.py
taf/foundation/api/plugins/mobileplugin.py
taf/foundation/api/plugins/restplugin.py
taf/foundation/api/plugins/webplugin.py
taf/foundation/api/svc/__init__.py
taf/foundation/api/svc/REST/__init__.py
taf/foundation/api/svc/REST/client.py
taf/foundation/api/ui/__init__.py
taf/foundation/api/ui/aut.py
taf/foundation/api/ui/uielement.py
taf/foundation/api/ui/controls/__init__.py
taf/foundation/api/ui/controls/button.py
taf/foundation/api/ui/controls/checkbox.py
taf/foundation/api/ui/controls/combobox.py
taf/foundation/api/ui/controls/edit.py
taf/foundation/api/ui/controls/frame.py
taf/foundation/api/ui/controls/link.py
taf/foundation/api/ui/controls/listitem.py
taf/foundation/api/ui/controls/radiogroup.py
taf/foundation/api/ui/controls/table.py
taf/foundation/api/ui/controls/text.py
taf/foundation/api/ui/mobile/__init__.py
taf/foundation/api/ui/patterns/__init__.py
taf/foundation/api/ui/patterns/basepattern.py
taf/foundation/api/ui/patterns/container.py
taf/foundation/api/ui/patterns/expandcollapse.py
taf/foundation/api/ui/patterns/grid.py
taf/foundation/api/ui/patterns/invoke.py
taf/foundation/api/ui/patterns/selection.py
taf/foundation/api/ui/patterns/selectionitem.py
taf/foundation/api/ui/patterns/table.py
taf/foundation/api/ui/patterns/text.py
taf/foundation/api/ui/patterns/toggle.py
taf/foundation/api/ui/patterns/value.py
taf/foundation/api/ui/support/__init__.py
taf/foundation/api/ui/support/elementfinder.py
taf/foundation/api/ui/support/locator.py
taf/foundation/api/ui/support/waithandler.py
taf/foundation/api/ui/web/__init__.py
taf/foundation/api/ui/web/browser.py
taf/foundation/api/ui/web/page.py
