Metadata-Version: 2.1
Name: PyXTaf
Version: 0.5.1.64
Summary: Extensible Test Automation Framework
Home-page: https://github.com/WesleyPeng/uiXautomation
Author: Wesley Peng
Author-email: wesley.peng@live.com
License: Apache License 2.0
Keywords: Automation Framework
Platform: posix
Classifier: Development Status :: 5 - Production/Stable
Classifier: Operating System :: POSIX :: Linux
Classifier: Programming Language :: Python :: 2.7
Classifier: Programming Language :: Python :: 3.6
Classifier: Programming Language :: Python :: 3.7
Classifier: Topic :: Software Development :: Libraries :: Python Modules
Classifier: Topic :: Software Development :: Testing
Requires-Python: >=2.7.9, <3.8
Requires-Dist: enum34 (>=1.1.6)
Requires-Dist: paramiko (>=1.16.0)
Requires-Dist: PyYAML (>=3.11)
Requires-Dist: requests (>=2.9.1)
Requires-Dist: Appium-Python-Client (>=0.24)
